{
    "items": [
        {
            "label": "677da422c4f2abe4cf06617e",
            "uri": "https://apps.openei.org/USURDB/rate/view/677da422c4f2abe4cf06617e",
            "revisions": [
                1736262066,
                1736262332
            ],
            "approved": true,
            "utility": "Georgia Power Co",
            "eiaid": 7140,
            "name": "Schedule PLS-18 Power and Light Small",
            "startdate": 1735689600,
            "supersedes": "668daccf4fd230141f045b8b",
            "sector": "Commercial",
            "description": "To all electric service of one standard voltage required on the customer's premises, delivered at one point and metered at or compensated to that voltage for any customer with a demand as determined under the Special Applicability Provisions, of less than 30 kW.",
            "source": "https://www.georgiapower.com/content/dam/georgia-power/pdfs/business-pdfs/tariffs/2025/pls-18.pdf",
            "sourceparent": "https://www.georgiapower.com/business/billing-and-rates/business-rates.html",
            "peakkwcapacitymax": 30,
            "voltagecategory": "Secondary",
            "phasewiring": "Single and 3-Phase",
            "flatdemandunit": "kW",
            "flatdemandstructure": [
                [
                    {
                        "max": 30,
                        "rate": 0
                    },
                    {
                        "rate": 11.29
                    }
                ]
            ],
            "flatdemandmonths": [
                0,
                0,
                0,
                0,
                0,
                0,
                0,
                0,
                0,
                0,
                0,
                0
            ],
            "demandrateunit": "kW",
            "energyratestructure": [
                [
                    {
                        "max": 200,
                        "unit": "kWh/kW",
                        "rate": 0,
                        "adj": 0.045876
                    },
                    {
                        "max": 25,
                        "unit": "kWh",
                        "rate": 0,
                        "adj": 0.045876
                    },
                    {
                        "max": 3000,
                        "unit": "kWh",
                        "rate": 0.159506,
                        "adj": 0.06914
                    },
                    {
                        "max": 10000,
                        "unit": "kWh",
                        "rate": 0.150142,
                        "adj": 0.06777
                    },
                    {
                        "max": 400,
                        "unit": "kWh/kW",
                        "rate": 0.130614,
                        "adj": 0.06493
                    },
                    {
                        "max": 600,
                        "unit": "kWh/kW",
                        "rate": 0.016092,
                        "adj": 0.04823
                    },
                    {
                        "unit": "kWh/kW",
                        "rate": 0.012194,
                        "adj": 0.04765
                    },
                    {
                        "unit": "kWh",
                        "rate": 0.01061,
                        "adj": 0.04742
                    }
                ],
                [
                    {
                        "max": 200,
                        "unit": "kWh/kW",
                        "rate": 0,
                        "adj": 0.042859
                    },
                    {
                        "max": 25,
                        "unit": "kWh",
                        "rate": 0,
                        "adj": 0.042859
                    },
                    {
                        "max": 3000,
                        "unit": "kWh",
                        "rate": 0.159506,
                        "adj": 0.06612
                    },
                    {
                        "max": 10000,
                        "unit": "kWh",
                        "rate": 0.150142,
                        "adj": 0.06475
                    },
                    {
                        "max": 400,
                        "unit": "kWh/kW",
                        "rate": 0.130614,
                        "adj": 0.06191
                    },
                    {
                        "max": 600,
                        "unit": "kWh/kW",
                        "rate": 0.016092,
                        "adj": 0.04521
                    },
                    {
                        "unit": "kWh/kW",
                        "rate": 0.012194,
                        "adj": 0.04463
                    },
                    {
                        "unit": "kWh",
                        "rate": 0.01061,
                        "adj": 0.0444
                    }
                ]
            ],
            "energyweekdayschedule": [
                [
                    1,
                    1,
                    1,
                    1,
                    1,
                    1,
                    1,
                    1,
                    1,
                    1,
                    1,
                    1,
                    1,
                    1,
                    1,
                    1,
                    1,
                    1,
                    1,
                    1,
                    1,
                    1,
                    1,
                    1
                ],
                [
                    1,
                    1,
                    1,
                    1,
                    1,
                    1,
                    1,
                    1,
                    1,
                    1,
                    1,
                    1,
                    1,
                    1,
                    1,
                    1,
                    1,
                    1,
                    1,
                    1,
                    1,
                    1,
                    1,
                    1
                ],
                [
                    1,
                    1,
                    1,
                    1,
                    1,
                    1,
                    1,
                    1,
                    1,
                    1,
                    1,
                    1,
                    1,
                    1,
                    1,
                    1,
                    1,
                    1,
                    1,
                    1,
                    1,
                    1,
                    1,
                    1
                ],
                [
                    1,
                    1,
                    1,
                    1,
                    1,
                    1,
                    1,
                    1,
                    1,
                    1,
                    1,
                    1,
                    1,
                    1,
                    1,
                    1,
                    1,
                    1,
                    1,
                    1,
                    1,
                    1,
                    1,
                    1
                ],
                [
                    1,
                    1,
                    1,
                    1,
                    1,
                    1,
                    1,
                    1,
                    1,
                    1,
                    1,
                    1,
                    1,
                    1,
                    1,
                    1,
                    1,
                    1,
                    1,
                    1,
                    1,
                    1,
                    1,
                    1
                ],
                [
                    0,
                    0,
                    0,
                    0,
                    0,
                    0,
                    0,
                    0,
                    0,
                    0,
                    0,
                    0,
                    0,
                    0,
                    0,
                    0,
                    0,
                    0,
                    0,
                    0,
                    0,
                    0,
                    0,
                    0
                ],
                [
                    0,
                    0,
                    0,
                    0,
                    0,
                    0,
                    0,
                    0,
                    0,
                    0,
                    0,
                    0,
                    0,
                    0,
                    0,
                    0,
                    0,
                    0,
                    0,
                    0,
                    0,
                    0,
                    0,
                    0
                ],
                [
                    0,
                    0,
                    0,
                    0,
                    0,
                    0,
                    0,
                    0,
                    0,
                    0,
                    0,
                    0,
                    0,
                    0,
                    0,
                    0,
                    0,
                    0,
                    0,
                    0,
                    0,
                    0,
                    0,
                    0
                ],
                [
                    0,
                    0,
                    0,
                    0,
                    0,
                    0,
                    0,
                    0,
                    0,
                    0,
                    0,
                    0,
                    0,
                    0,
                    0,
                    0,
                    0,
                    0,
                    0,
                    0,
                    0,
                    0,
                    0,
                    0
                ],
                [
                    1,
                    1,
                    1,
                    1,
                    1,
                    1,
                    1,
                    1,
                    1,
                    1,
                    1,
                    1,
                    1,
                    1,
                    1,
                    1,
                    1,
                    1,
                    1,
                    1,
                    1,
                    1,
                    1,
                    1
                ],
                [
                    1,
                    1,
                    1,
                    1,
                    1,
                    1,
                    1,
                    1,
                    1,
                    1,
                    1,
                    1,
                    1,
                    1,
                    1,
                    1,
                    1,
                    1,
                    1,
                    1,
                    1,
                    1,
                    1,
                    1
                ],
                [
                    1,
                    1,
                    1,
                    1,
                    1,
                    1,
                    1,
                    1,
                    1,
                    1,
                    1,
                    1,
                    1,
                    1,
                    1,
                    1,
                    1,
                    1,
                    1,
                    1,
                    1,
                    1,
                    1,
                    1
                ]
            ],
            "energyweekendschedule": [
                [
                    1,
                    1,
                    1,
                    1,
                    1,
                    1,
                    1,
                    1,
                    1,
                    1,
                    1,
                    1,
                    1,
                    1,
                    1,
                    1,
                    1,
                    1,
                    1,
                    1,
                    1,
                    1,
                    1,
                    1
                ],
                [
                    1,
                    1,
                    1,
                    1,
                    1,
                    1,
                    1,
                    1,
                    1,
                    1,
                    1,
                    1,
                    1,
                    1,
                    1,
                    1,
                    1,
                    1,
                    1,
                    1,
                    1,
                    1,
                    1,
                    1
                ],
                [
                    1,
                    1,
                    1,
                    1,
                    1,
                    1,
                    1,
                    1,
                    1,
                    1,
                    1,
                    1,
                    1,
                    1,
                    1,
                    1,
                    1,
                    1,
                    1,
                    1,
                    1,
                    1,
                    1,
                    1
                ],
                [
                    1,
                    1,
                    1,
                    1,
                    1,
                    1,
                    1,
                    1,
                    1,
                    1,
                    1,
                    1,
                    1,
                    1,
                    1,
                    1,
                    1,
                    1,
                    1,
                    1,
                    1,
                    1,
                    1,
                    1
                ],
                [
                    1,
                    1,
                    1,
                    1,
                    1,
                    1,
                    1,
                    1,
                    1,
                    1,
                    1,
                    1,
                    1,
                    1,
                    1,
                    1,
                    1,
                    1,
                    1,
                    1,
                    1,
                    1,
                    1,
                    1
                ],
                [
                    0,
                    0,
                    0,
                    0,
                    0,
                    0,
                    0,
                    0,
                    0,
                    0,
                    0,
                    0,
                    0,
                    0,
                    0,
                    0,
                    0,
                    0,
                    0,
                    0,
                    0,
                    0,
                    0,
                    0
                ],
                [
                    0,
                    0,
                    0,
                    0,
                    0,
                    0,
                    0,
                    0,
                    0,
                    0,
                    0,
                    0,
                    0,
                    0,
                    0,
                    0,
                    0,
                    0,
                    0,
                    0,
                    0,
                    0,
                    0,
                    0
                ],
                [
                    0,
                    0,
                    0,
                    0,
                    0,
                    0,
                    0,
                    0,
                    0,
                    0,
                    0,
                    0,
                    0,
                    0,
                    0,
                    0,
                    0,
                    0,
                    0,
                    0,
                    0,
                    0,
                    0,
                    0
                ],
                [
                    0,
                    0,
                    0,
                    0,
                    0,
                    0,
                    0,
                    0,
                    0,
                    0,
                    0,
                    0,
                    0,
                    0,
                    0,
                    0,
                    0,
                    0,
                    0,
                    0,
                    0,
                    0,
                    0,
                    0
                ],
                [
                    1,
                    1,
                    1,
                    1,
                    1,
                    1,
                    1,
                    1,
                    1,
                    1,
                    1,
                    1,
                    1,
                    1,
                    1,
                    1,
                    1,
                    1,
                    1,
                    1,
                    1,
                    1,
                    1,
                    1
                ],
                [
                    1,
                    1,
                    1,
                    1,
                    1,
                    1,
                    1,
                    1,
                    1,
                    1,
                    1,
                    1,
                    1,
                    1,
                    1,
                    1,
                    1,
                    1,
                    1,
                    1,
                    1,
                    1,
                    1,
                    1
                ],
                [
                    1,
                    1,
                    1,
                    1,
                    1,
                    1,
                    1,
                    1,
                    1,
                    1,
                    1,
                    1,
                    1,
                    1,
                    1,
                    1,
                    1,
                    1,
                    1,
                    1,
                    1,
                    1,
                    1,
                    1
                ]
            ],
            "energycomments": "Adjustments = Environmental Compliance Cost Recovery + Demand Side Management + Fuel Cost Recovery",
            "fixedmonthlycharge": 38
        },
        {
            "label": "677da328afaf0738a30cd89a",
            "uri": "https://apps.openei.org/USURDB/rate/view/677da328afaf0738a30cd89a",
            "revisions": [
                1736261816,
                1736262029
            ],
            "approved": true,
            "utility": "Georgia Power Co",
            "eiaid": 7140,
            "name": "Irrigation Off-Peak Service IOP-21",
            "startdate": 1735689600,
            "supersedes": "668db3c24fd230141f045b8c",
            "sector": "Commercial",
            "description": "To all Commercial and Industrial electric service of one standard voltage required on the customer's\r\npremises, delivered at one point and metered at or compensated to that voltage for irrigation purposes\r\nduring Off-Peak period. The customer may be responsible to the Company for any additional cost of installing and removing any equipment required to control, meter or deliver this service",
            "source": "https://www.georgiapower.com/content/dam/georgia-power/pdfs/business-pdfs/tariffs/2025/iop-21.pdf",
            "sourceparent": "https://www.georgiapower.com/business/billing-and-rates/business-rates.html",
            "basicinformationcomments": "The rate structure of this rate does not fit the database structure, please visit the website for more details",
            "voltagecategory": "Secondary",
            "phasewiring": "Single and 3-Phase",
            "flatdemandunit": "kW",
            "demandrateunit": "kW",
            "energyratestructure": [
                [
                    {
                        "max": 200,
                        "unit": "kWh/kW",
                        "rate": 0,
                        "adj": 0.042859
                    },
                    {
                        "max": 3000,
                        "unit": "kWh",
                        "rate": 0.17076,
                        "adj": 0.06776
                    },
                    {
                        "max": 5000,
                        "unit": "kWh",
                        "rate": 0.154653,
                        "adj": 0.06541
                    },
                    {
                        "max": 5001,
                        "unit": "kWh",
                        "rate": 0.017415,
                        "adj": 0.04539
                    },
                    {
                        "unit": "kWh/kW",
                        "rate": 0.017415,
                        "adj": 0.04539
                    }
                ],
                [
                    {
                        "max": 200,
                        "unit": "kWh/kW",
                        "rate": 0,
                        "adj": 0.045876
                    },
                    {
                        "max": 3000,
                        "unit": "kWh",
                        "rate": 0.17076,
                        "adj": 0.07078
                    },
                    {
                        "max": 5000,
                        "unit": "kWh",
                        "rate": 0.154653,
                        "adj": 0.06843
                    },
                    {
                        "max": 5001,
                        "unit": "kWh",
                        "rate": 0.017415,
                        "adj": 0.04841
                    },
                    {
                        "unit": "kWh/kW",
                        "rate": 0.017415,
                        "adj": 0.04841
                    }
                ]
            ],
            "energyweekdayschedule": [
                [
                    0,
                    0,
                    0,
                    0,
                    0,
                    0,
                    0,
                    0,
                    0,
                    0,
                    0,
                    0,
                    0,
                    0,
                    0,
                    0,
                    0,
                    0,
                    0,
                    0,
                    0,
                    0,
                    0,
                    0
                ],
                [
                    0,
                    0,
                    0,
                    0,
                    0,
                    0,
                    0,
                    0,
                    0,
                    0,
                    0,
                    0,
                    0,
                    0,
                    0,
                    0,
                    0,
                    0,
                    0,
                    0,
                    0,
                    0,
                    0,
                    0
                ],
                [
                    0,
                    0,
                    0,
                    0,
                    0,
                    0,
                    0,
                    0,
                    0,
                    0,
                    0,
                    0,
                    0,
                    0,
                    0,
                    0,
                    0,
                    0,
                    0,
                    0,
                    0,
                    0,
                    0,
                    0
                ],
                [
                    0,
                    0,
                    0,
                    0,
                    0,
                    0,
                    0,
                    0,
                    0,
                    0,
                    0,
                    0,
                    0,
                    0,
                    0,
                    0,
                    0,
                    0,
                    0,
                    0,
                    0,
                    0,
                    0,
                    0
                ],
                [
                    0,
                    0,
                    0,
                    0,
                    0,
                    0,
                    0,
                    0,
                    0,
                    0,
                    0,
                    0,
                    0,
                    0,
                    0,
                    0,
                    0,
                    0,
                    0,
                    0,
                    0,
                    0,
                    0,
                    0
                ],
                [
                    1,
                    1,
                    1,
                    1,
                    1,
                    1,
                    1,
                    1,
                    1,
                    1,
                    1,
                    1,
                    1,
                    1,
                    1,
                    1,
                    1,
                    1,
                    1,
                    1,
                    1,
                    1,
                    1,
                    1
                ],
                [
                    1,
                    1,
                    1,
                    1,
                    1,
                    1,
                    1,
                    1,
                    1,
                    1,
                    1,
                    1,
                    1,
                    1,
                    1,
                    1,
                    1,
                    1,
                    1,
                    1,
                    1,
                    1,
                    1,
                    1
                ],
                [
                    1,
                    1,
                    1,
                    1,
                    1,
                    1,
                    1,
                    1,
                    1,
                    1,
                    1,
                    1,
                    1,
                    1,
                    1,
                    1,
                    1,
                    1,
                    1,
                    1,
                    1,
                    1,
                    1,
                    1
                ],
                [
                    1,
                    1,
                    1,
                    1,
                    1,
                    1,
                    1,
                    1,
                    1,
                    1,
                    1,
                    1,
                    1,
                    1,
                    1,
                    1,
                    1,
                    1,
                    1,
                    1,
                    1,
                    1,
                    1,
                    1
                ],
                [
                    0,
                    0,
                    0,
                    0,
                    0,
                    0,
                    0,
                    0,
                    0,
                    0,
                    0,
                    0,
                    0,
                    0,
                    0,
                    0,
                    0,
                    0,
                    0,
                    0,
                    0,
                    0,
                    0,
                    0
                ],
                [
                    0,
                    0,
                    0,
                    0,
                    0,
                    0,
                    0,
                    0,
                    0,
                    0,
                    0,
                    0,
                    0,
                    0,
                    0,
                    0,
                    0,
                    0,
                    0,
                    0,
                    0,
                    0,
                    0,
                    0
                ],
                [
                    0,
                    0,
                    0,
                    0,
                    0,
                    0,
                    0,
                    0,
                    0,
                    0,
                    0,
                    0,
                    0,
                    0,
                    0,
                    0,
                    0,
                    0,
                    0,
                    0,
                    0,
                    0,
                    0,
                    0
                ]
            ],
            "energyweekendschedule": [
                [
                    0,
                    0,
                    0,
                    0,
                    0,
                    0,
                    0,
                    0,
                    0,
                    0,
                    0,
                    0,
                    0,
                    0,
                    0,
                    0,
                    0,
                    0,
                    0,
                    0,
                    0,
                    0,
                    0,
                    0
                ],
                [
                    0,
                    0,
                    0,
                    0,
                    0,
                    0,
                    0,
                    0,
                    0,
                    0,
                    0,
                    0,
                    0,
                    0,
                    0,
                    0,
                    0,
                    0,
                    0,
                    0,
                    0,
                    0,
                    0,
                    0
                ],
                [
                    0,
                    0,
                    0,
                    0,
                    0,
                    0,
                    0,
                    0,
                    0,
                    0,
                    0,
                    0,
                    0,
                    0,
                    0,
                    0,
                    0,
                    0,
                    0,
                    0,
                    0,
                    0,
                    0,
                    0
                ],
                [
                    0,
                    0,
                    0,
                    0,
                    0,
                    0,
                    0,
                    0,
                    0,
                    0,
                    0,
                    0,
                    0,
                    0,
                    0,
                    0,
                    0,
                    0,
                    0,
                    0,
                    0,
                    0,
                    0,
                    0
                ],
                [
                    0,
                    0,
                    0,
                    0,
                    0,
                    0,
                    0,
                    0,
                    0,
                    0,
                    0,
                    0,
                    0,
                    0,
                    0,
                    0,
                    0,
                    0,
                    0,
                    0,
                    0,
                    0,
                    0,
                    0
                ],
                [
                    1,
                    1,
                    1,
                    1,
                    1,
                    1,
                    1,
                    1,
                    1,
                    1,
                    1,
                    1,
                    1,
                    1,
                    1,
                    1,
                    1,
                    1,
                    1,
                    1,
                    1,
                    1,
                    1,
                    1
                ],
                [
                    1,
                    1,
                    1,
                    1,
                    1,
                    1,
                    1,
                    1,
                    1,
                    1,
                    1,
                    1,
                    1,
                    1,
                    1,
                    1,
                    1,
                    1,
                    1,
                    1,
                    1,
                    1,
                    1,
                    1
                ],
                [
                    1,
                    1,
                    1,
                    1,
                    1,
                    1,
                    1,
                    1,
                    1,
                    1,
                    1,
                    1,
                    1,
                    1,
                    1,
                    1,
                    1,
                    1,
                    1,
                    1,
                    1,
                    1,
                    1,
                    1
                ],
                [
                    1,
                    1,
                    1,
                    1,
                    1,
                    1,
                    1,
                    1,
                    1,
                    1,
                    1,
                    1,
                    1,
                    1,
                    1,
                    1,
                    1,
                    1,
                    1,
                    1,
                    1,
                    1,
                    1,
                    1
                ],
                [
                    0,
                    0,
                    0,
                    0,
                    0,
                    0,
                    0,
                    0,
                    0,
                    0,
                    0,
                    0,
                    0,
                    0,
                    0,
                    0,
                    0,
                    0,
                    0,
                    0,
                    0,
                    0,
                    0,
                    0
                ],
                [
                    0,
                    0,
                    0,
                    0,
                    0,
                    0,
                    0,
                    0,
                    0,
                    0,
                    0,
                    0,
                    0,
                    0,
                    0,
                    0,
                    0,
                    0,
                    0,
                    0,
                    0,
                    0,
                    0,
                    0
                ],
                [
                    0,
                    0,
                    0,
                    0,
                    0,
                    0,
                    0,
                    0,
                    0,
                    0,
                    0,
                    0,
                    0,
                    0,
                    0,
                    0,
                    0,
                    0,
                    0,
                    0,
                    0,
                    0,
                    0,
                    0
                ]
            ],
            "energycomments": "Adjustments = Environmental Compliance Cost Recovery + Demand Side Management + Fuel Cost Recovery",
            "fixedmonthlycharge": 43
        },
        {
            "label": "677da290ee81823f200d73c9",
            "uri": "https://apps.openei.org/USURDB/rate/view/677da290ee81823f200d73c9",
            "revisions": [
                1736261664,
                1736261777
            ],
            "approved": true,
            "utility": "Georgia Power Co",
            "eiaid": 7140,
            "name": "SCHEDULE APS-16 AGRICULTURAL PROCESS SERVICE RATE",
            "startdate": 1735689600,
            "supersedes": "668db589d56a31719f0a34b2",
            "sector": "Industrial",
            "description": "APPLICABILITY:\r\nApplicable to establishments that provide processing or storage services of agricultural products to individually owned farm operations. For the purposes of this rate schedule, processing or storage service means that ownership of the product before, during, and immediately after processing or storage remains\r\nwith the individually owned farm operation, and the processing or storage service provider is paid on a fee per unit basis. Individually owned farm operations that process or store their own product also qualify. Examples of types of operations that could qualify are cotton gins and vegetable or fruit storage facilities. More than fifty percent (50%) of the processing service provider's business must meet these criteria in order to qualify. The customer will be responsible to the Company for any additional cost of installing and removing any equipment required to control, meter or deliver this service. This electric service shall be delivered at one point, at one standard voltage and metered at or compensated to that voltage.\r\n\r\nApplicable with riders: ECCR, DSM-R-4, NCCR-3, MFF-2, and LT-1.",
            "source": "https://www.georgiapower.com/content/dam/georgia-power/pdfs/business-pdfs/tariffs/2025/aps-17.pdf",
            "sourceparent": "https://www.georgiapower.com/business/billing-and-rates/business-rates.html",
            "flatdemandunit": "kW",
            "flatdemandstructure": [
                [
                    {
                        "rate": 8.13
                    }
                ],
                [
                    {
                        "rate": 27.59
                    }
                ]
            ],
            "flatdemandmonths": [
                0,
                0,
                0,
                0,
                0,
                1,
                1,
                1,
                1,
                0,
                0,
                0
            ],
            "demandrateunit": "kW",
            "energyratestructure": [
                [
                    {
                        "unit": "kWh",
                        "rate": 0.022774,
                        "adj": 0.04618
                    }
                ],
                [
                    {
                        "unit": "kWh",
                        "rate": 0.022774,
                        "adj": 0.0492
                    }
                ]
            ],
            "energyweekdayschedule": [
                [
                    0,
                    0,
                    0,
                    0,
                    0,
                    0,
                    0,
                    0,
                    0,
                    0,
                    0,
                    0,
                    0,
                    0,
                    0,
                    0,
                    0,
                    0,
                    0,
                    0,
                    0,
                    0,
                    0,
                    0
                ],
                [
                    0,
                    0,
                    0,
                    0,
                    0,
                    0,
                    0,
                    0,
                    0,
                    0,
                    0,
                    0,
                    0,
                    0,
                    0,
                    0,
                    0,
                    0,
                    0,
                    0,
                    0,
                    0,
                    0,
                    0
                ],
                [
                    0,
                    0,
                    0,
                    0,
                    0,
                    0,
                    0,
                    0,
                    0,
                    0,
                    0,
                    0,
                    0,
                    0,
                    0,
                    0,
                    0,
                    0,
                    0,
                    0,
                    0,
                    0,
                    0,
                    0
                ],
                [
                    0,
                    0,
                    0,
                    0,
                    0,
                    0,
                    0,
                    0,
                    0,
                    0,
                    0,
                    0,
                    0,
                    0,
                    0,
                    0,
                    0,
                    0,
                    0,
                    0,
                    0,
                    0,
                    0,
                    0
                ],
                [
                    0,
                    0,
                    0,
                    0,
                    0,
                    0,
                    0,
                    0,
                    0,
                    0,
                    0,
                    0,
                    0,
                    0,
                    0,
                    0,
                    0,
                    0,
                    0,
                    0,
                    0,
                    0,
                    0,
                    0
                ],
                [
                    1,
                    1,
                    1,
                    1,
                    1,
                    1,
                    1,
                    1,
                    1,
                    1,
                    1,
                    1,
                    1,
                    1,
                    1,
                    1,
                    1,
                    1,
                    1,
                    1,
                    1,
                    1,
                    1,
                    1
                ],
                [
                    1,
                    1,
                    1,
                    1,
                    1,
                    1,
                    1,
                    1,
                    1,
                    1,
                    1,
                    1,
                    1,
                    1,
                    1,
                    1,
                    1,
                    1,
                    1,
                    1,
                    1,
                    1,
                    1,
                    1
                ],
                [
                    1,
                    1,
                    1,
                    1,
                    1,
                    1,
                    1,
                    1,
                    1,
                    1,
                    1,
                    1,
                    1,
                    1,
                    1,
                    1,
                    1,
                    1,
                    1,
                    1,
                    1,
                    1,
                    1,
                    1
                ],
                [
                    1,
                    1,
                    1,
                    1,
                    1,
                    1,
                    1,
                    1,
                    1,
                    1,
                    1,
                    1,
                    1,
                    1,
                    1,
                    1,
                    1,
                    1,
                    1,
                    1,
                    1,
                    1,
                    1,
                    1
                ],
                [
                    0,
                    0,
                    0,
                    0,
                    0,
                    0,
                    0,
                    0,
                    0,
                    0,
                    0,
                    0,
                    0,
                    0,
                    0,
                    0,
                    0,
                    0,
                    0,
                    0,
                    0,
                    0,
                    0,
                    0
                ],
                [
                    0,
                    0,
                    0,
                    0,
                    0,
                    0,
                    0,
                    0,
                    0,
                    0,
                    0,
                    0,
                    0,
                    0,
                    0,
                    0,
                    0,
                    0,
                    0,
                    0,
                    0,
                    0,
                    0,
                    0
                ],
                [
                    0,
                    0,
                    0,
                    0,
                    0,
                    0,
                    0,
                    0,
                    0,
                    0,
                    0,
                    0,
                    0,
                    0,
                    0,
                    0,
                    0,
                    0,
                    0,
                    0,
                    0,
                    0,
                    0,
                    0
                ]
            ],
            "energyweekendschedule": [
                [
                    0,
                    0,
                    0,
                    0,
                    0,
                    0,
                    0,
                    0,
                    0,
                    0,
                    0,
                    0,
                    0,
                    0,
                    0,
                    0,
                    0,
                    0,
                    0,
                    0,
                    0,
                    0,
                    0,
                    0
                ],
                [
                    0,
                    0,
                    0,
                    0,
                    0,
                    0,
                    0,
                    0,
                    0,
                    0,
                    0,
                    0,
                    0,
                    0,
                    0,
                    0,
                    0,
                    0,
                    0,
                    0,
                    0,
                    0,
                    0,
                    0
                ],
                [
                    0,
                    0,
                    0,
                    0,
                    0,
                    0,
                    0,
                    0,
                    0,
                    0,
                    0,
                    0,
                    0,
                    0,
                    0,
                    0,
                    0,
                    0,
                    0,
                    0,
                    0,
                    0,
                    0,
                    0
                ],
                [
                    0,
                    0,
                    0,
                    0,
                    0,
                    0,
                    0,
                    0,
                    0,
                    0,
                    0,
                    0,
                    0,
                    0,
                    0,
                    0,
                    0,
                    0,
                    0,
                    0,
                    0,
                    0,
                    0,
                    0
                ],
                [
                    0,
                    0,
                    0,
                    0,
                    0,
                    0,
                    0,
                    0,
                    0,
                    0,
                    0,
                    0,
                    0,
                    0,
                    0,
                    0,
                    0,
                    0,
                    0,
                    0,
                    0,
                    0,
                    0,
                    0
                ],
                [
                    1,
                    1,
                    1,
                    1,
                    1,
                    1,
                    1,
                    1,
                    1,
                    1,
                    1,
                    1,
                    1,
                    1,
                    1,
                    1,
                    1,
                    1,
                    1,
                    1,
                    1,
                    1,
                    1,
                    1
                ],
                [
                    1,
                    1,
                    1,
                    1,
                    1,
                    1,
                    1,
                    1,
                    1,
                    1,
                    1,
                    1,
                    1,
                    1,
                    1,
                    1,
                    1,
                    1,
                    1,
                    1,
                    1,
                    1,
                    1,
                    1
                ],
                [
                    1,
                    1,
                    1,
                    1,
                    1,
                    1,
                    1,
                    1,
                    1,
                    1,
                    1,
                    1,
                    1,
                    1,
                    1,
                    1,
                    1,
                    1,
                    1,
                    1,
                    1,
                    1,
                    1,
                    1
                ],
                [
                    1,
                    1,
                    1,
                    1,
                    1,
                    1,
                    1,
                    1,
                    1,
                    1,
                    1,
                    1,
                    1,
                    1,
                    1,
                    1,
                    1,
                    1,
                    1,
                    1,
                    1,
                    1,
                    1,
                    1
                ],
                [
                    0,
                    0,
                    0,
                    0,
                    0,
                    0,
                    0,
                    0,
                    0,
                    0,
                    0,
                    0,
                    0,
                    0,
                    0,
                    0,
                    0,
                    0,
                    0,
                    0,
                    0,
                    0,
                    0,
                    0
                ],
                [
                    0,
                    0,
                    0,
                    0,
                    0,
                    0,
                    0,
                    0,
                    0,
                    0,
                    0,
                    0,
                    0,
                    0,
                    0,
                    0,
                    0,
                    0,
                    0,
                    0,
                    0,
                    0,
                    0,
                    0
                ],
                [
                    0,
                    0,
                    0,
                    0,
                    0,
                    0,
                    0,
                    0,
                    0,
                    0,
                    0,
                    0,
                    0,
                    0,
                    0,
                    0,
                    0,
                    0,
                    0,
                    0,
                    0,
                    0,
                    0,
                    0
                ]
            ],
            "energycomments": "Adjustments = Environmental Compliance Cost Recovery + Demand Side Management + Fuel Cost Recovery",
            "fixedmonthlycharge": 43
        }
    ]
}